examally/__init__.py
flaskk/__init__.py
flask_labtest-1.0.1.dist-info/METADATA
flask_labtest-1.0.1.dist-info/WHEEL
flask_labtest-1.0.1.dist-info/top_level.txt
flask_labtest-1.0.1.dist-info/RECORD
